{
  "updatedAt": "2026-07-20T05:46:06Z",
  "packs": [
    {
      "name": "Akatsuki",
      "java": null,
      "bedrock": "https://raw.githubusercontent.com/Net2027/Packiran/main/Pack/Akatsuki/Bedrock/Akatsuki.rar",
      "description": "سازگار با نسخه 1.21 به بالا"
    },
    {
      "name": "Batman",
      "java": null,
      "bedrock": "https://raw.githubusercontent.com/Net2027/Packiran/main/Pack/Batman/Bedrock/batman_32x.rar",
      "description": "سازگار با نسخه 1.21 به بالا"
    },
    {
      "name": "Fat cat",
      "java": null,
      "bedrock": "https://raw.githubusercontent.com/Net2027/Packiran/main/Pack/Fat%20cat/Bedrock/Fat%20Cat%20%5B16x%5D(1).rar",
      "description": "سازگار با نسخه 1.21 به بالا"
    },
    {
      "name": "Jason voorhees",
      "java": null,
      "bedrock": "https://raw.githubusercontent.com/Net2027/Packiran/main/Pack/Jason%20voorhees/Bedrock/jason%20voorhees%20%5BBedrock%5D.rar",
      "description": "سازگار با نسخه 1.21 به بالا"
    },
    {
      "name": "Kepler",
      "java": null,
      "bedrock": "https://raw.githubusercontent.com/Net2027/Packiran/main/Pack/Kepler/Bedrock/Kepler%20%5BBedrock%5D.rar",
      "description": "سازگار با نسخه 1.21 به بالا"
    },
    {
      "name": "Rigel",
      "java": null,
      "bedrock": "https://raw.githubusercontent.com/Net2027/Packiran/main/Pack/Rigel/Bedrock/Rigel%20%5BBedrock%5D.rar",
      "description": "سازگار با نسخه 1.21 به بالا"
    },
    {
      "name": "Sunflower",
      "java": null,
      "bedrock": "https://raw.githubusercontent.com/Net2027/Packiran/main/Pack/Sunflower/Bedrock/Sunflower.rar",
      "description": "سازگار با نسخه 1.21 به بالا"
    },
    {
      "name": "Tangerine",
      "java": null,
      "bedrock": "https://raw.githubusercontent.com/Net2027/Packiran/main/Pack/Tangerine/Bedrock/Tangerine%20-%20SamStrix%205K%20Texture%20Pack%20%5BBedrock%5D.rar",
      "description": "سازگار با نسخه 1.21 به بالا"
    },
    {
      "name": "Tlaloc",
      "java": null,
      "bedrock": "https://raw.githubusercontent.com/Net2027/Packiran/main/Pack/Tlaloc/Bedrock/Tlaloc%20%5BBedrock%5D.rar",
      "description": "سازگار با نسخه 1.21 به بالا"
    },
    {
      "name": "Todoroki",
      "java": null,
      "bedrock": "https://raw.githubusercontent.com/Net2027/Packiran/main/Pack/Todoroki/Bedrock/Todoroki.rar",
      "description": "سازگار با نسخه 1.21 به بالا"
    },
    {
      "name": "Venom",
      "java": null,
      "bedrock": "https://raw.githubusercontent.com/Net2027/Packiran/main/Pack/Venom/Bedrock/Venom16x.rar",
      "description": "سازگار با نسخه 1.21 به بالا"
    }
  ],
  "mods": [
    {
      "name": "Lucky-SkyBlock",
      "file": "https://raw.githubusercontent.com/Net2027/Packiran/main/Mod/Lucky-SkyBlock/File/Lucky%20BlockSkyblock%20(1).mctemplate",
      "description": "بدراک 1.20 به بالا",
      "compatibility": "سازگار بدراک"
    },
    {
      "name": "اکشن اند استاف نسخه 1.11 (جدید ترین نسخه )",
      "file": "https://raw.githubusercontent.com/Net2027/Packiran/main/Mod/اکشن اند استاف نسخه 1.11 (جدید ترین نسخه )/File/Actions%20Stuff%201.11%20.mcpack",
      "description": "بدراک 1.26.30 به بالا",
      "compatibility": "سازگار بدراک"
    },
    {
      "name": "مود ساخت شهر",
      "file": "https://raw.githubusercontent.com/Net2027/Packiran/main/Mod/مود ساخت شهر/File/City%20Expansion%20Add-On%20(addon).mcaddon",
      "description": "بدراک 1.20 به بالا",
      "compatibility": "سازگار بدراک"
    }
  ],
  "shaders": [
    {
      "name": "اکشن اند استاف 1.11(جدید ترین نسخه )",
      "file": "https://raw.githubusercontent.com/Net2027/Packiran/main/Shader/اکشن اند استاف 1.11(جدید ترین نسخه )/File/Actions%20Stuff%201.11",
      "description": "نسخه 1.26.30 به بالا",
      "compatibility": "سازگار با بدراک"
    }
  ],
  "films": [],
  "downloads": []
}